{
	"class" : {
		 },
	"instance" : {
		"addFunctionCalled:in:" : "LeonardoHumbertoSilva 11/9/2014 16:40",
		"addFunctionInstanceField:in:" : "LeonardoHumbertoSilva 11/9/2014 08:33",
		"addJSChild:in:" : "LeonardoHumbertoSilva 11/13/2014 08:02",
		"addJSClass:withNew:" : "LeonardoHumbertoSilva 11/13/2014 07:57",
		"addJSConstructor:in:" : "LeonardoHumbertoSilva 10/4/2014 15:49",
		"addJSField:in:key:" : "LeonardoHumbertoSilva 11/7/2014 10:41",
		"addJSFieldPreConditionsOk:in:key:" : "LeonardoHumbertoSilva 10/23/2014 08:52",
		"addJSFunction:" : "LeonardoHumbertoSilva 11/9/2014 08:34",
		"addJSMethod:in:key:" : "LeonardoHumbertoSilva 10/12/2014 10:44",
		"addJSMethod:in:key:params:" : "LeonardoHumbertoSilva 11/7/2014 15:43",
		"addJSMethodPreConditionsOk:in:key:params:" : "LeonardoHumbertoSilva 11/7/2014 15:42",
		"addJSMethodShortName:in:" : "LeonardoHumbertoSilva 10/12/2014 10:42",
		"addJSParent:in:" : "LeonardoHumbertoSilva 11/10/2014 07:31",
		"calcDPT:" : "LeonardoHumbertoSilva 11/6/2014 10:47",
		"calcLCOM:in:" : "LeonardoHumbertoSilva 11/9/2014 15:09",
		"calcNOA:" : "LeonardoHumbertoSilva 11/8/2014 09:47",
		"calcNOC:" : "LeonardoHumbertoSilva 11/10/2014 07:43",
		"calcNOCA:" : "LeonardoHumbertoSilva 11/6/2014 10:58",
		"calcNOCM:" : "LeonardoHumbertoSilva 11/6/2014 14:18",
		"calcNOPA:" : "LeonardoHumbertoSilva 11/6/2014 14:14",
		"calcNOPM:" : "LeonardoHumbertoSilva 11/6/2014 14:20",
		"callHeuristics2:at:" : "LeonardoHumbertoSilva 11/13/2014 11:04",
		"checkDiffFunctionTypesH1:" : "LeonardoHumbertoSilva 9/20/2014 14:18",
		"checkExpressionFieldsH1H4:" : "LeonardoHumbertoSilva 10/9/2014 08:47",
		"checkExpressionMethodsH1H4:" : "LeonardoHumbertoSilva 11/13/2014 15:49",
		"checkHeuristicsForPrototypeDepth:" : "LeonardoHumbertoSilva 11/10/2014 07:57",
		"getChildNameHI1:" : "LeonardoHumbertoSilva 10/11/2014 15:17",
		"getJSClasses" : "LeonardoHumbertoSilva 8/30/2014 10:15",
		"getJSFunctions" : "LeonardoHumbertoSilva 11/7/2014 10:26",
		"getParentNameHI1:" : "LeonardoHumbertoSilva 9/15/2014 08:55",
		"getParentNameHI2:" : "LeonardoHumbertoSilva 10/11/2014 15:19",
		"initialize" : "LeonardoHumbertoSilva 11/6/2014 15:56",
		"isAFunction:" : "LeonardoHumbertoSilva 11/7/2014 15:00",
		"isFieldValueAFunction:" : "LeonardoHumbertoSilva 11/7/2014 15:24",
		"isFunctionInstanceField:in:" : "LeonardoHumbertoSilva 11/8/2014 21:18",
		"isJSField:in:key:" : "LeonardoHumbertoSilva 10/6/2014 14:58",
		"isJSMethod:in:key:" : "LeonardoHumbertoSilva 10/23/2014 08:51",
		"isPrototypeMethod:" : "LeonardoHumbertoSilva 9/20/2014 13:29",
		"listJSClasses" : "LeonardoHumbertoSilva 11/13/2014 09:01",
		"listJSFunctions" : "LeonardoHumbertoSilva 11/9/2014 16:42",
		"listOOMetrics" : "LeonardoHumbertoSilva 11/13/2014 09:11",
		"listOOMetricsCSV" : "LeonardoHumbertoSilva 10/21/2014 08:49",
		"methodFunctionName:in:" : "LeonardoHumbertoSilva 11/9/2014 11:50",
		"navigateJSONStructure:at:" : "LeonardoHumbertoSilva 11/9/2014 17:41",
		"navigateJSONStructure:in:target:" : "LeonardoHumbertoSilva 11/13/2014 14:19",
		"preConditionsHI2:" : "LeonardoHumbertoSilva 10/21/2014 08:30",
		"printClassElements:" : "LeonardoHumbertoSilva 9/4/2014 16:06",
		"removeClassesWithoutConstructor" : "LeonardoHumbertoSilva 11/13/2014 18:40",
		"scriptMultipleSystems:" : "LeonardoHumbertoSilva 11/6/2014 10:34",
		"searchClassDefinitionH1:" : "LeonardoHumbertoSilva 10/2/2014 09:38",
		"searchClassDefinitionH1_2:" : "LeonardoHumbertoSilva 10/12/2014 09:01",
		"searchClassElements:" : "LeonardoHumbertoSilva 11/13/2014 08:38",
		"searchClassElementsH1:" : "LeonardoHumbertoSilva 10/2/2014 09:51",
		"searchClassElementsH1_2:" : "LeonardoHumbertoSilva 11/13/2014 09:07",
		"searchClassInstantiation:" : "LeonardoHumbertoSilva 11/13/2014 07:59",
		"searchClassNameInstantiation:" : "LeonardoHumbertoSilva 11/9/2014 08:46",
		"searchClassNameNoPrototypeH1:" : "LeonardoHumbertoSilva 9/20/2014 14:02",
		"searchClasses:" : "LeonardoHumbertoSilva 10/29/2014 09:39",
		"searchExpressionElementsH1:" : "LeonardoHumbertoSilva 10/2/2014 09:52",
		"searchExpressionElementsH1_2:" : "LeonardoHumbertoSilva 10/14/2014 08:42",
		"searchFunctionCall:" : "LeonardoHumbertoSilva 11/9/2014 18:35",
		"searchFunctionInstanceField:" : "LeonardoHumbertoSilva 11/8/2014 21:47",
		"searchJSClassH1:" : "LeonardoHumbertoSilva 10/5/2014 17:39",
		"searchJSClassH1_2:" : "LeonardoHumbertoSilva 10/11/2014 16:30",
		"searchJSClassH2:" : "LeonardoHumbertoSilva 10/2/2014 09:58",
		"searchJSClassH2_2:" : "LeonardoHumbertoSilva 11/13/2014 11:10",
		"searchJSClassH3:" : "LeonardoHumbertoSilva 10/30/2014 09:42",
		"searchJSClassName:" : "LeonardoHumbertoSilva 11/13/2014 08:26",
		"searchJSFieldExpression:in:" : "LeonardoHumbertoSilva 11/8/2014 09:37",
		"searchJSFieldNameH1:" : "LeonardoHumbertoSilva 10/5/2014 17:22",
		"searchJSFieldVariable:in:" : "LeonardoHumbertoSilva 10/5/2014 17:29",
		"searchJSFields:in:" : "LeonardoHumbertoSilva 9/9/2014 14:45",
		"searchJSFields_2:in:" : "LeonardoHumbertoSilva 10/12/2014 10:17",
		"searchJSFunctions:" : "LeonardoHumbertoSilva 11/9/2014 18:33",
		"searchJSMethodNameH1:" : "LeonardoHumbertoSilva 10/4/2014 11:03",
		"searchJSMethodNameH4:" : "LeonardoHumbertoSilva 10/4/2014 11:02",
		"searchJSMethodsH2:in:" : "LeonardoHumbertoSilva 10/4/2014 11:13",
		"searchJSMethodsH2_2:in:" : "LeonardoHumbertoSilva 10/13/2014 10:31",
		"searchJSMethodsH3:in:" : "LeonardoHumbertoSilva 11/13/2014 19:01",
		"searchJSMethodsH3_2:in:" : "LeonardoHumbertoSilva 11/13/2014 19:03",
		"searchJSONFiles:" : "LeonardoHumbertoSilva 10/30/2014 10:04",
		"searchJSParams:" : "LeonardoHumbertoSilva 9/8/2014 15:00",
		"searchJSPrototypeDepth:" : "LeonardoHumbertoSilva 10/11/2014 15:08",
		"searchVariableElementsH1:" : "LeonardoHumbertoSilva 10/2/2014 09:54",
		"searchVariableElementsH1_2:" : "LeonardoHumbertoSilva 10/14/2014 08:44",
		"searchVariableFunction:" : "LeonardoHumbertoSilva 11/9/2014 18:05",
		"setConstructorInfo:in:" : "LeonardoHumbertoSilva 11/13/2014 19:42",
		"writeOOMetricsCSV:" : "LeonardoHumbertoSilva 11/11/2014 21:27" } }
